{
  "main": {
    "id": "b94e85b0a99faa67",
    "type": "split",
    "children": [
      {
        "id": "c99b84bee654d33e",
        "type": "tabs",
        "children": [
          {
            "id": "2b47173c5bb25ca5",
            "type": "leaf",
            "state": {
              "type": "markdown",
              "state": {
                "file": "SPSS/假設檢定.md",
                "mode": "source",
                "source": false
              }
            }
          },
          {
            "id": "5e381708cf05361e",
            "type": "leaf",
            "state": {
              "type": "markdown",
              "state": {
                "file": "SPSS/交叉分析與卡方檢定.md",
                "mode": "source",
                "source": false
              }
            }
          },
          {
            "id": "9d4b7cfb06e80e10",
            "type": "leaf",
            "state": {
              "type": "markdown",
              "state": {
                "file": "SPSS/T檢定.md",
                "mode": "source",
                "source": false
              }
            }
          },
          {
            "id": "49e5d6cc9db163c3",
            "type": "leaf",
            "state": {
              "type": "markdown",
              "state": {
                "file": "變異數分析（ANOVA）.md",
                "mode": "source",
                "source": false
              }
            }
          }
        ],
        "currentTab": 3
      }
    ],
    "direction": "vertical"
  },
  "left": {
    "id": "5c9dc2b853bb42c2",
    "type": "split",
    "children": [
      {
        "id": "94545a4ffe72edbb",
        "type": "tabs",
        "children": [
          {
            "id": "4cf2ae5e2e5e1670",
            "type": "leaf",
            "state": {
              "type": "file-explorer",
              "state": {
                "sortOrder": "alphabetical"
              }
            }
          },
          {
            "id": "4a3da70176c7d39e",
            "type": "leaf",
            "state": {
              "type": "search",
              "state": {
                "query": "tag:collaborative_learning",
                "matchingCase": false,
                "explainSearch": false,
                "collapseAll": false,
                "extraContext": false,
                "sortOrder": "alphabetical"
              }
            }
          },
          {
            "id": "94b0de54bf892431",
            "type": "leaf",
            "state": {
              "type": "bookmarks",
              "state": {}
            }
          }
        ]
      }
    ],
    "direction": "horizontal",
    "width": 242.5
  },
  "right": {
    "id": "f881b5380496a60f",
    "type": "split",
    "children": [
      {
        "id": "45f4383817774283",
        "type": "tabs",
        "children": [
          {
            "id": "df22487ee4c38ef3",
            "type": "leaf",
            "state": {
              "type": "backlink",
              "state": {
                "file": "變異數分析（ANOVA）.md",
                "collapseAll": false,
                "extraContext": false,
                "sortOrder": "alphabetical",
                "showSearch": false,
                "searchQuery": "",
                "backlinkCollapsed": false,
                "unlinkedCollapsed": true
              }
            }
          },
          {
            "id": "a452adec9251a9bf",
            "type": "leaf",
            "state": {
              "type": "outgoing-link",
              "state": {
                "file": "變異數分析（ANOVA）.md",
                "linksCollapsed": false,
                "unlinkedCollapsed": true
              }
            }
          },
          {
            "id": "3131b8e42c7996f4",
            "type": "leaf",
            "state": {
              "type": "tag",
              "state": {
                "sortOrder": "frequency",
                "useHierarchy": true
              }
            }
          },
          {
            "id": "a3eaca24b94b1233",
            "type": "leaf",
            "state": {
              "type": "outline",
              "state": {
                "file": "變異數分析（ANOVA）.md"
              }
            }
          }
        ],
        "currentTab": 3
      }
    ],
    "direction": "horizontal",
    "width": 218.5
  },
  "left-ribbon": {
    "hiddenItems": {
      "switcher:開啟快速切換": false,
      "graph:查看關聯圖": false,
      "canvas:建立新畫布": false,
      "daily-notes:開啟今天的每日筆記": false,
      "templates:插入模板": false,
      "command-palette:開啟命令面板": false
    }
  },
  "active": "49e5d6cc9db163c3",
  "lastOpenFiles": [
    "SPSS/T檢定.md",
    "變異數分析（ANOVA）.md",
    "SPSS/相關分析.md",
    "SPSS/假設檢定.md",
    "SPSS/交叉分析與卡方檢定.md",
    "交叉分析.md",
    "SPSS/多變量簡介.md",
    "SPSS/敘述性統計.md",
    "SPSS/README.md",
    "README.md",
    "統計學/緒論.md",
    "SPSS/中介分析（meidation analysis）.md",
    "SPSS/範例檔/敘述性統計/MLB2019_1.sav",
    "SPSS/範例檔/敘述性統計/MLB2019.sav",
    "SPSS/範例檔/敘述性統計/~$MLB Salary 2019.xlsx",
    "SPSS/範例檔/敘述性統計/MLB Salary 2019.xlsx",
    "SPSS/範例檔/敘述性統計",
    "SPSS/範例檔/未命名檔案夾",
    "SPSS/範例檔/MLB Salary 2019.xlsx",
    "SPSS/MLB Salary 2019.xlsx",
    "SPSS/集中趨勢（central tendency）.md",
    "SPSS/SPSS軟體基本操作.md",
    "世燁老師這邊的報告/2024.05.05 實作心得.md",
    "attachments/Pasted image 20240504181021.png",
    "SPSS/範例檔/spss_4_data.zip",
    "SPSS/範例檔",
    "統計學/機率.md",
    "TCP.md",
    "隨機變數.md",
    "世燁老師這邊的報告/【數位雙生AR】demo/2014.04.16【數位雙生AR】簡報重點.md",
    "硬體基本知識.md",
    "英文雜誌/2024.04 ALL+.md",
    "世燁老師這邊的論文/未閱讀/異常感測ssensor/2021 Smart Anomaly Detection in Sensor Systems A Multi-Perspective Review.md",
    "世燁老師這邊的論文/合作學習/2022 Cooperative and Collaborative Learning An Innovation in Teaching Medical Physiology.md",
    "世燁老師這邊的論文/XR（VR AR MR）/2021 The Effects of Virtual Reality, Augmented Reality, and Mixed Reality as Training Enhancement Methods.md",
    "世燁老師這邊的論文/XR（VR AR MR）/2020 An Immersive Multi-User Virtual Reality for Emergency Simulation Training Usability Study.md",
    "世燁老師這邊的論文/醫療領域/2022 Cooperative and Collaborative Learning An Innovation in Teaching Medical Physiology.md",
    "英文雜誌/attachments/截圖 2024-04-10 凌晨1.33.07.png",
    "英文雜誌/attachments/截圖 2024-04-09 凌晨12.49.29.png",
    "英文雜誌/attachments/截圖 2024-04-09 凌晨12.48.45.png",
    "attachments/截圖 2024-04-08 下午2.59.47.png",
    "attachments/Pasted image 20240406170624.png",
    "attachments/截圖 2024-04-06 凌晨1.51.19.png",
    "attachments/截圖 2024-04-06 凌晨1.48.29.png",
    "attachments/截圖 2024-04-06 凌晨1.44.44.png",
    "attachments/截圖 2024-04-06 凌晨1.30.48.png",
    "未命名.canvas"
  ]
}